testHD/__init__.py
testHD/__version__.py
testHD/aa.py
testHD/bb.py
testHD/cc.py
testHD/log.py
testHD-0.1.9.dist-info/METADATA
testHD-0.1.9.dist-info/WHEEL
testHD-0.1.9.dist-info/top_level.txt
testHD-0.1.9.dist-info/RECORD
