Metadata-Version: 2.1
Name: testHD
Version: 0.1.9
Summary: This is a package for test HD
Home-page: https://github.com/jhj0203/Portfolio.git
Author: HaeDream
Author-email: jhj990203@gmail.com
Classifier: Programming Language :: Python :: 3
Classifier: License :: OSI Approved :: MIT License
Classifier: Operating System :: OS Independent
Requires-Python: >=3.6
